{
  "$schema": "https://ui.shadcn.com/schema/registry-item.json",
  "name": "dotm-square-7",
  "type": "registry:ui",
  "title": "Block Drop",
  "description": "Tetromino-like frames drop and stack in a 5x5 matrix, then flash a row-clear beat.",
  "dependencies": [],
  "registryDependencies": [],
  "meta": {
    "animation": "css-only"
  },
  "files": [
    {
      "path": "components/ui/dotm-square-7.tsx",
      "type": "registry:ui"
    },
    {
      "path": "components/ui/dotmatrix-core.tsx",
      "type": "registry:lib"
    },
    {
      "path": "components/ui/dotmatrix-hooks.ts",
      "type": "registry:lib"
    },
    {
      "path": "styles/dotmatrix-loader.css",
      "type": "registry:style"
    }
  ]
}
